README.md
setup.py
grtracer/__init__.py
grtracer.egg-info/PKG-INFO
grtracer.egg-info/SOURCES.txt
grtracer.egg-info/dependency_links.txt
grtracer.egg-info/not-zip-safe
grtracer.egg-info/requires.txt
grtracer.egg-info/top_level.txt
grtracer/flask/__init__.py