Metadata-Version: 1.0
Name: grtracer
Version: 1.2.3
Summary: Simple tracing setup using Jaeger and Flask
Home-page: https://github.com/ryzokuken/grtracer
Author: Ujjwal Sharma
Author-email: usharma1998@gmail.com
License: MIT
Platform: UNKNOWN
